{"entities":{"pages":{"Terv":{"id":"Terv","title":"Hazsnáltautó","url":"terv.html","level":0,"tabIndex":0},"Adatbázis":{"id":"Adatbázis","title":"Adatbázis","url":"adatbázis.html","level":0,"tabIndex":1},"Funkciók":{"id":"Funkciók","title":"Funkciók","url":"funkciók.html","level":0,"pages":["Hirdetések","Hitelesítés","Böngészés","Kommentek"],"tabIndex":2},"Hirdetések":{"id":"Hirdetések","title":"Hirdetések","url":"hirdetések.html","level":1,"parentId":"Funkciók","pages":["Hirdetés","Hirdetés-módosítása","Hirdetés-törlése","Képfeltöltés","Saját-hirdetések-nézet"],"tabIndex":0},"Hirdetés":{"id":"Hirdetés","title":"Hirdetés feladása","url":"hirdetés.html","level":2,"parentId":"Hirdetések","tabIndex":0},"Hirdetés-módosítása":{"id":"Hirdetés-módosítása","title":"Hirdetés módosítása","url":"hirdetés-módosítása.html","level":2,"parentId":"Hirdetések","tabIndex":1},"Hirdetés-törlése":{"id":"Hirdetés-törlése","title":"Hirdetés törlése","url":"hirdetés-törlése.html","level":2,"parentId":"Hirdetések","tabIndex":2},"Képfeltöltés":{"id":"Képfeltöltés","title":"Képfeltöltés","url":"képfeltöltés.html","level":2,"parentId":"Hirdetések","tabIndex":3},"Saját-hirdetések-nézet":{"id":"Saját-hirdetések-nézet","title":"Saját hirdetések nézet","url":"saját-hirdetések-nézet.html","level":2,"parentId":"Hirdetések","tabIndex":4},"Hitelesítés":{"id":"Hitelesítés","title":"Hitelesítés","url":"hitelesítés.html","level":1,"parentId":"Funkciók","pages":["Elfelejtett-jelszó","Bejelentkezés","Regisztráció"],"tabIndex":1},"Elfelejtett-jelszó":{"id":"Elfelejtett-jelszó","title":"Elfelejtett jelszó","url":"elfelejtett-jelszó.html","level":2,"parentId":"Hitelesítés","tabIndex":0},"Bejelentkezés":{"id":"Bejelentkezés","title":"Bejelentkezés","url":"bejelentkezés.html","level":2,"parentId":"Hitelesítés","tabIndex":1},"Regisztráció":{"id":"Regisztráció","title":"Regisztráció","url":"regisztráció.html","level":2,"parentId":"Hitelesítés","tabIndex":2},"Böngészés":{"id":"Böngészés","title":"Böngészés","url":"böngészés.html","level":1,"parentId":"Funkciók","tabIndex":2},"Kommentek":{"id":"Kommentek","title":"Kommentek","url":"kommentek.html","level":1,"parentId":"Funkciók","tabIndex":3},"Tesztelés":{"id":"Tesztelés","title":"Tesztelés","url":"tesztelés.html","level":0,"pages":["Test-Users"],"tabIndex":3},"Test-Users":{"id":"Test-Users","title":"Teszt felhasználói adatok","url":"test-users.html","level":1,"parentId":"Tesztelés","tabIndex":0},"Munkamegosztás":{"id":"Munkamegosztás","title":"Munkamegosztás","url":"munkamegosztás.html","level":0,"tabIndex":4}}},"topLevelIds":["Terv","Adatbázis","Funkciók","Tesztelés","Munkamegosztás"]}